{
  "boundary_functional_present": true,
  "candidate_count": 3,
  "limitations": [
    "The v1.2 boundary functional is action-linked and available, but not a standalone complete mirror-exclusion theorem."
  ],
  "open_obligations": [
    "derive v1.2 boundary-functional mirror exclusion from the full kernel boundary problem"
  ],
  "standalone_exclusion_proven": false,
  "status": "BOUNDARY_MIRROR_CHANNEL_CONDITIONAL",
  "theorem_complete": false,
  "title": "BHSM v2.3 Boundary Mirror Channel Report"
}
