{
  "assumptions": [
    "P_perp is an orthogonal bounded projector on the formal sector-labeled Hilbert space.",
    "D(A0+V)=D(A0) and the graph norms are equivalent.",
    "All nonzero commutators are controlled by v2.14."
  ],
  "control_constant": 2.0476067054442755,
  "domain_invariance_status": "PROJECTOR_DOMAIN_INVARIANCE_PROVEN",
  "graph_norm_equivalence": true,
  "inequality": "||P_perp psi||_(A0+V) <= C ||psi||_(A0+V)",
  "interacting_domain_status": "INTERACTING_DOMAIN_EQUALS_REFERENCE_DOMAIN_PROVEN",
  "limitations": [
    "The graph-norm control closes projector-domain stability only.",
    "Lower-bound transfer and index/mirror theorem gates remain separate."
  ],
  "projector_bounded_on_D_A0": true,
  "projector_bounded_on_D_A0V": true,
  "projector_bounded_on_H": true,
  "status": "PROJECTOR_GRAPH_NORM_CONTROL_PROVEN",
  "theorem_complete": true,
  "title": "BHSM v2.15 Projector Graph-Norm Control Report"
}
